astroph_new/__init__.py
astroph_new/astroph_new.py
astroph_new-0.2.4.dist-info/LICENSE
astroph_new-0.2.4.dist-info/WHEEL
astroph_new-0.2.4.dist-info/METADATA
astroph_new-0.2.4.dist-info/RECORD
