Metadata-Version: 2.1
Name: astroph_new
Version: 0.2.4
Summary: python module to make summary of astro-ph based on user interests
Author-email: Shinyoung Kim <radioshiny@gmail.com>
Requires-Python: >=3.7
Classifier: Programming Language :: Python :: 3
Classifier: Programming Language :: Python :: 3.9
Classifier: License :: OSI Approved :: MIT License
Requires-Dist: bs4
Requires-Dist: numpy
Requires-Dist: selenium
Requires-Dist: whoswho
Project-URL: Documentation, https://astroph-new.readthedocs.io
Project-URL: Source, https://github.com/radioshiny/astroph_new
